uproot/__init__.py
uproot/_awkwardforth.py
uproot/_dask.py
uproot/_util.py
uproot/behavior.py
uproot/cache.py
uproot/compression.py
uproot/const.py
uproot/containers.py
uproot/deserialization.py
uproot/dynamic.py
uproot/exceptions.py
uproot/extras.py
uproot/model.py
uproot/pyroot.py
uproot/reading.py
uproot/serialization.py
uproot/streamers.py
uproot/version.py
uproot/behaviors/RNTuple.py
uproot/behaviors/RooCurve.py
uproot/behaviors/RooHist.py
uproot/behaviors/TAxis.py
uproot/behaviors/TBranch.py
uproot/behaviors/TBranchElement.py
uproot/behaviors/TDatime.py
uproot/behaviors/TGraph.py
uproot/behaviors/TGraphAsymmErrors.py
uproot/behaviors/TGraphErrors.py
uproot/behaviors/TH1.py
uproot/behaviors/TH2.py
uproot/behaviors/TH2Poly.py
uproot/behaviors/TH3.py
uproot/behaviors/TParameter.py
uproot/behaviors/TProfile.py
uproot/behaviors/TProfile2D.py
uproot/behaviors/TProfile3D.py
uproot/behaviors/TTree.py
uproot/behaviors/__init__.py
uproot/interpretation/__init__.py
uproot/interpretation/custom.py
uproot/interpretation/grouped.py
uproot/interpretation/identify.py
uproot/interpretation/jagged.py
uproot/interpretation/library.py
uproot/interpretation/numerical.py
uproot/interpretation/objects.py
uproot/interpretation/strings.py
uproot/interpretation/known_forth/__init__.py
uproot/interpretation/known_forth/atlas.py
uproot/language/__init__.py
uproot/language/python.py
uproot/models/RNTuple.py
uproot/models/TArray.py
uproot/models/TAtt.py
uproot/models/TBasket.py
uproot/models/TBranch.py
uproot/models/TClonesArray.py
uproot/models/TDatime.py
uproot/models/TGraph.py
uproot/models/TH.py
uproot/models/THashList.py
uproot/models/TLeaf.py
uproot/models/TList.py
uproot/models/TMatrixT.py
uproot/models/TNamed.py
uproot/models/TObjArray.py
uproot/models/TObjString.py
uproot/models/TObject.py
uproot/models/TRef.py
uproot/models/TString.py
uproot/models/TTable.py
uproot/models/TTime.py
uproot/models/TTree.py
uproot/models/__init__.py
uproot/sink/__init__.py
uproot/sink/file.py
uproot-5.7.0.dist-info/METADATA
uproot-5.7.0.dist-info/WHEEL
uproot-5.7.0.dist-info/licenses/LICENSE
uproot-5.7.0.dist-info/RECORD
