Metadata-Version: 2.4
Name: uproot
Version: 5.7.0
Summary: ROOT I/O in pure Python and NumPy.
Project-URL: Download, https://github.com/scikit-hep/uproot5/releases
Project-URL: Homepage, https://github.com/scikit-hep/uproot5
Author-email: Jim Pivarski <jpivarski@gmail.com>
License-Expression: BSD-3-Clause
License-File: LICENSE
Classifier: Development Status :: 5 - Production/Stable
Classifier: Intended Audience :: Developers
Classifier: Intended Audience :: Information Technology
Classifier: Intended Audience :: Science/Research
Classifier: Operating System :: MacOS
Classifier: Operating System :: POSIX
Classifier: Operating System :: Unix
Classifier: Programming Language :: Python
Classifier: Programming Language :: Python :: 3
Classifier: Programming Language :: Python :: 3 :: Only
Classifier: Programming Language :: Python :: 3.10
Classifier: Programming Language :: Python :: 3.11
Classifier: Programming Language :: Python :: 3.12
Classifier: Programming Language :: Python :: 3.13
Classifier: Programming Language :: Python :: 3.14
Classifier: Topic :: Scientific/Engineering
Classifier: Topic :: Scientific/Engineering :: Information Analysis
Classifier: Topic :: Scientific/Engineering :: Mathematics
Classifier: Topic :: Scientific/Engineering :: Physics
Classifier: Topic :: Software Development
Classifier: Topic :: Utilities
Requires-Python: >=3.10
Requires-Dist: awkward>=2.8.2
Requires-Dist: cramjam>=2.5.0
Requires-Dist: fsspec!=2025.7.0
Requires-Dist: numpy
Requires-Dist: packaging
Requires-Dist: typing-extensions>=4.1.0; python_version < '3.11'
Requires-Dist: xxhash
Provides-Extra: gds-cu11
Requires-Dist: kvikio-cu11>=25.02.01; extra == 'gds-cu11'
Provides-Extra: gds-cu12
Requires-Dist: kvikio-cu12>=25.02.01; extra == 'gds-cu12'
Provides-Extra: http
Requires-Dist: aiohttp; extra == 'http'
Provides-Extra: s3
Requires-Dist: s3fs; extra == 's3'
Provides-Extra: xrootd
Requires-Dist: fsspec-xrootd>=0.5.0; extra == 'xrootd'
